{"@bean": "com.cyoda.core.model.stateMachine.dto.FullWorkflowContainerDto", "workflow": [{"persisted": true, "owner": "CYODA", "id": "55280b92-40ad-11f0-9476-2e9782bd5fa7", "name": "pet:1000:58cbeac6-3f0f-11b2-ba20-3e7b56738ce4", "entityClassName": "com.cyoda.tdb.model.treenode.TreeNodeEntity", "creationDate": "2025-06-03T19:02:45.069+00:00", "description": "Workflow managing pet lifecycle including search, add, update, and delete operations.", "entityShortClassName": "TreeNodeEntity", "transitionIds": ["55281178-40ad-11f0-9476-2e9782bd5fa7", "55282064-40ad-11f0-9476-2e9782bd5fa7", "55282c26-40ad-11f0-9476-2e9782bd5fa7", "55283928-40ad-11f0-9476-2e9782bd5fa7"], "criteriaIds": ["55280eb2-40ad-11f0-9476-2e9782bd5fa7"], "stateIds": ["noneState"], "active": true, "useDecisionTree": false, "decisionTrees": [], "metaData": {"documentLink": ""}}], "transitions": [{"persisted": true, "owner": "CYODA", "id": "55281178-40ad-11f0-9476-2e9782bd5fa7", "name": "start_search", "entityClassName": "com.cyoda.tdb.model.treenode.TreeNodeEntity", "creationDate": "2025-06-03T19:02:45.069+00:00", "description": "Start searching pets", "startStateId": "noneState", "endStateId": "55281d80-40ad-11f0-9476-2e9782bd5fa7", "workflowId": "55280b92-40ad-11f0-9476-2e9782bd5fa7", "criteriaIds": [], "endProcessesIds": [{"persisted": true, "persistedId": "5528124a-40ad-11f0-9476-2e9782bd5fa7", "runtimeId": 0}], "active": true, "automated": true, "logActivity": false}, {"persisted": true, "owner": "CYODA", "id": "55282064-40ad-11f0-9476-2e9782bd5fa7", "name": "search_to_add", "entityClassName": "com.cyoda.tdb.model.treenode.TreeNodeEntity", "creationDate": "2025-06-03T19:02:45.070+00:00", "description": "Transition from searched to adding a pet", "startStateId": "55281d80-40ad-11f0-9476-2e9782bd5fa7", "endStateId": "55282a6e-40ad-11f0-9476-2e9782bd5fa7", "workflowId": "55280b92-40ad-11f0-9476-2e9782bd5fa7", "criteriaIds": [], "endProcessesIds": [{"persisted": true, "persistedId": "5528212c-40ad-11f0-9476-2e9782bd5fa7", "runtimeId": 0}], "active": true, "automated": true, "logActivity": false}, {"persisted": true, "owner": "CYODA", "id": "55282c26-40ad-11f0-9476-2e9782bd5fa7", "name": "add_to_update", "entityClassName": "com.cyoda.tdb.model.treenode.TreeNodeEntity", "creationDate": "2025-06-03T19:02:45.070+00:00", "description": "Transition from added to updating pet details", "startStateId": "55282a6e-40ad-11f0-9476-2e9782bd5fa7", "endStateId": "55283658-40ad-11f0-9476-2e9782bd5fa7", "workflowId": "55280b92-40ad-11f0-9476-2e9782bd5fa7", "criteriaIds": [], "endProcessesIds": [{"persisted": true, "persistedId": "55282cda-40ad-11f0-9476-2e9782bd5fa7", "runtimeId": 0}], "active": true, "automated": true, "logActivity": false}, {"persisted": true, "owner": "CYODA", "id": "55283928-40ad-11f0-9476-2e9782bd5fa7", "name": "update_to_delete", "entityClassName": "com.cyoda.tdb.model.treenode.TreeNodeEntity", "creationDate": "2025-06-03T19:02:45.070+00:00", "description": "Transition from updated to deleting the pet", "startStateId": "55283658-40ad-11f0-9476-2e9782bd5fa7", "endStateId": "552843dc-40ad-11f0-9476-2e9782bd5fa7", "workflowId": "55280b92-40ad-11f0-9476-2e9782bd5fa7", "criteriaIds": [], "endProcessesIds": [{"persisted": true, "persistedId": "552839e6-40ad-11f0-9476-2e9782bd5fa7", "runtimeId": 0}], "active": true, "automated": true, "logActivity": false}], "criterias": [{"persisted": true, "owner": "CYODA", "id": "55280eb2-40ad-11f0-9476-2e9782bd5fa7", "name": "pet:1000:58cbeac6-3f0f-11b2-ba20-3e7b56738ce4", "entityClassName": "com.cyoda.tdb.model.treenode.TreeNodeEntity", "creationDate": "2025-06-03T19:02:45.069+00:00", "description": "Workflow criteria", "condition": {"@bean": "com.cyoda.core.conditions.GroupCondition", "operator": "AND", "conditions": [{"@bean": "com.cyoda.core.conditions.queryable.Equals", "fieldName": "entityModelName", "operation": "EQUALS", "rangeField": "false", "value": "pet"}, {"@bean": "com.cyoda.core.conditions.queryable.Equals", "fieldName": "entityModelVersion", "operation": "EQUALS", "rangeField": "false", "value": 1000.0}]}, "aliasDefs": [], "parameters": [], "criteriaChecker": "ConditionCriteriaChecker", "user": "CYODA"}], "processes": [{"persisted": true, "owner": "CYODA", "id": {"@bean": "com.cyoda.core.model.stateMachine.dto.ProcessIdDto", "persisted": true, "persistedId": "5528124a-40ad-11f0-9476-2e9782bd5fa7", "runtimeId": 0}, "name": "process_pet_search", "entityClassName": "com.cyoda.tdb.model.treenode.TreeNodeEntity", "creationDate": "2025-06-03T19:02:45.069+00:00", "description": "", "processorClassName": "net.cyoda.saas.externalize.processor.ExternalizedProcessor", "parameters": [{"persisted": true, "owner": "CYODA", "id": "552812f4-40ad-11f0-9476-2e9782bd5fa7", "name": "Tags for filtering calculation nodes (separated by ',' or ';')", "creationDate": "2025-06-03T19:02:45.069+00:00", "valueType": "STRING", "value": {"@type": "String", "value": "58cbeac6-3f0f-11b2-ba20-3e7b56738ce4"}}, {"persisted": true, "owner": "CYODA", "id": "5528154c-40ad-11f0-9476-2e9782bd5fa7", "name": "Attach entity", "creationDate": "2025-06-03T19:02:45.069+00:00", "valueType": "STRING", "value": {"@type": "String", "value": "true"}}, {"persisted": true, "owner": "CYODA", "id": "5528172c-40ad-11f0-9476-2e9782bd5fa7", "name": "Calculation response timeout (ms)", "creationDate": "2025-06-03T19:02:45.069+00:00", "valueType": "INTEGER", "value": {"@type": "String", "value": "120000"}}, {"persisted": true, "owner": "CYODA", "id": "55281970-40ad-11f0-9476-2e9782bd5fa7", "name": "Retry policy", "creationDate": "2025-06-03T19:02:45.069+00:00", "valueType": "STRING", "value": {"@type": "String", "value": "NONE"}}], "fields": [], "syncProcess": false, "newTransactionForAsync": true, "noneTransactionalForAsync": false, "isTemplate": false, "criteriaIds": [], "user": "CYODA"}, {"persisted": true, "owner": "CYODA", "id": {"@bean": "com.cyoda.core.model.stateMachine.dto.ProcessIdDto", "persisted": true, "persistedId": "5528212c-40ad-11f0-9476-2e9782bd5fa7", "runtimeId": 0}, "name": "process_pet_add", "entityClassName": "com.cyoda.tdb.model.treenode.TreeNodeEntity", "creationDate": "2025-06-03T19:02:45.070+00:00", "description": "", "processorClassName": "net.cyoda.saas.externalize.processor.ExternalizedProcessor", "parameters": [{"persisted": true, "owner": "CYODA", "id": "552821d6-40ad-11f0-9476-2e9782bd5fa7", "name": "Tags for filtering calculation nodes (separated by ',' or ';')", "creationDate": "2025-06-03T19:02:45.069+00:00", "valueType": "STRING", "value": {"@type": "String", "value": "58cbeac6-3f0f-11b2-ba20-3e7b56738ce4"}}, {"persisted": true, "owner": "CYODA", "id": "55282398-40ad-11f0-9476-2e9782bd5fa7", "name": "Attach entity", "creationDate": "2025-06-03T19:02:45.069+00:00", "valueType": "STRING", "value": {"@type": "String", "value": "true"}}, {"persisted": true, "owner": "CYODA", "id": "55282578-40ad-11f0-9476-2e9782bd5fa7", "name": "Calculation response timeout (ms)", "creationDate": "2025-06-03T19:02:45.069+00:00", "valueType": "INTEGER", "value": {"@type": "String", "value": "120000"}}, {"persisted": true, "owner": "CYODA", "id": "5528274e-40ad-11f0-9476-2e9782bd5fa7", "name": "Retry policy", "creationDate": "2025-06-03T19:02:45.070+00:00", "valueType": "STRING", "value": {"@type": "String", "value": "NONE"}}], "fields": [], "syncProcess": false, "newTransactionForAsync": true, "noneTransactionalForAsync": false, "isTemplate": false, "criteriaIds": [], "user": "CYODA"}, {"persisted": true, "owner": "CYODA", "id": {"@bean": "com.cyoda.core.model.stateMachine.dto.ProcessIdDto", "persisted": true, "persistedId": "55282cda-40ad-11f0-9476-2e9782bd5fa7", "runtimeId": 0}, "name": "process_pet_update", "entityClassName": "com.cyoda.tdb.model.treenode.TreeNodeEntity", "creationDate": "2025-06-03T19:02:45.070+00:00", "description": "", "processorClassName": "net.cyoda.saas.externalize.processor.ExternalizedProcessor", "parameters": [{"persisted": true, "owner": "CYODA", "id": "55282d98-40ad-11f0-9476-2e9782bd5fa7", "name": "Tags for filtering calculation nodes (separated by ',' or ';')", "creationDate": "2025-06-03T19:02:45.070+00:00", "valueType": "STRING", "value": {"@type": "String", "value": "58cbeac6-3f0f-11b2-ba20-3e7b56738ce4"}}, {"persisted": true, "owner": "CYODA", "id": "55282f78-40ad-11f0-9476-2e9782bd5fa7", "name": "Attach entity", "creationDate": "2025-06-03T19:02:45.070+00:00", "valueType": "STRING", "value": {"@type": "String", "value": "true"}}, {"persisted": true, "owner": "CYODA", "id": "55283162-40ad-11f0-9476-2e9782bd5fa7", "name": "Calculation response timeout (ms)", "creationDate": "2025-06-03T19:02:45.070+00:00", "valueType": "INTEGER", "value": {"@type": "String", "value": "120000"}}, {"persisted": true, "owner": "CYODA", "id": "55283356-40ad-11f0-9476-2e9782bd5fa7", "name": "Retry policy", "creationDate": "2025-06-03T19:02:45.070+00:00", "valueType": "STRING", "value": {"@type": "String", "value": "NONE"}}], "fields": [], "syncProcess": false, "newTransactionForAsync": true, "noneTransactionalForAsync": false, "isTemplate": false, "criteriaIds": [], "user": "CYODA"}, {"persisted": true, "owner": "CYODA", "id": {"@bean": "com.cyoda.core.model.stateMachine.dto.ProcessIdDto", "persisted": true, "persistedId": "552839e6-40ad-11f0-9476-2e9782bd5fa7", "runtimeId": 0}, "name": "process_pet_delete", "entityClassName": "com.cyoda.tdb.model.treenode.TreeNodeEntity", "creationDate": "2025-06-03T19:02:45.070+00:00", "description": "", "processorClassName": "net.cyoda.saas.externalize.processor.ExternalizedProcessor", "parameters": [{"persisted": true, "owner": "CYODA", "id": "55283a90-40ad-11f0-9476-2e9782bd5fa7", "name": "Tags for filtering calculation nodes (separated by ',' or ';')", "creationDate": "2025-06-03T19:02:45.070+00:00", "valueType": "STRING", "value": {"@type": "String", "value": "58cbeac6-3f0f-11b2-ba20-3e7b56738ce4"}}, {"persisted": true, "owner": "CYODA", "id": "55283c52-40ad-11f0-9476-2e9782bd5fa7", "name": "Attach entity", "creationDate": "2025-06-03T19:02:45.070+00:00", "valueType": "STRING", "value": {"@type": "String", "value": "true"}}, {"persisted": true, "owner": "CYODA", "id": "55283e64-40ad-11f0-9476-2e9782bd5fa7", "name": "Calculation response timeout (ms)", "creationDate": "2025-06-03T19:02:45.070+00:00", "valueType": "INTEGER", "value": {"@type": "String", "value": "120000"}}, {"persisted": true, "owner": "CYODA", "id": "5528408a-40ad-11f0-9476-2e9782bd5fa7", "name": "Retry policy", "creationDate": "2025-06-03T19:02:45.070+00:00", "valueType": "STRING", "value": {"@type": "String", "value": "NONE"}}], "fields": [], "syncProcess": false, "newTransactionForAsync": true, "noneTransactionalForAsync": false, "isTemplate": false, "criteriaIds": [], "user": "CYODA"}], "states": [{"persisted": true, "owner": "CYODA", "id": "noneState", "name": "None", "entityClassName": "com.cyoda.tdb.model.treenode.TreeNodeEntity", "creationDate": "2025-06-03T19:02:45.069+00:00", "description": "Initial state of the workflow."}, {"persisted": true, "owner": "CYODA", "id": "55281d80-40ad-11f0-9476-2e9782bd5fa7", "name": "Searched", "entityClassName": "com.cyoda.tdb.model.treenode.TreeNodeEntity", "creationDate": "2025-06-03T19:02:45.069+00:00", "description": "Pets have been searched"}, {"persisted": true, "owner": "CYODA", "id": "55282a6e-40ad-11f0-9476-2e9782bd5fa7", "name": "Added", "entityClassName": "com.cyoda.tdb.model.treenode.TreeNodeEntity", "creationDate": "2025-06-03T19:02:45.070+00:00", "description": "A pet has been added"}, {"persisted": true, "owner": "CYODA", "id": "55283658-40ad-11f0-9476-2e9782bd5fa7", "name": "Updated", "entityClassName": "com.cyoda.tdb.model.treenode.TreeNodeEntity", "creationDate": "2025-06-03T19:02:45.070+00:00", "description": "Pet details have been updated"}, {"persisted": true, "owner": "CYODA", "id": "552843dc-40ad-11f0-9476-2e9782bd5fa7", "name": "Deleted", "entityClassName": "com.cyoda.tdb.model.treenode.TreeNodeEntity", "creationDate": "2025-06-03T19:02:45.070+00:00", "description": "Pet has been deleted"}], "processParams": [{"persisted": true, "owner": "CYODA", "id": "552812f4-40ad-11f0-9476-2e9782bd5fa7", "name": "Tags for filtering calculation nodes (separated by ',' or ';')", "creationDate": "2025-06-03T19:02:45.069+00:00", "valueType": "STRING", "value": {"@type": "String", "value": "58cbeac6-3f0f-11b2-ba20-3e7b56738ce4"}}, {"persisted": true, "owner": "CYODA", "id": "5528154c-40ad-11f0-9476-2e9782bd5fa7", "name": "Attach entity", "creationDate": "2025-06-03T19:02:45.069+00:00", "valueType": "STRING", "value": {"@type": "String", "value": "true"}}, {"persisted": true, "owner": "CYODA", "id": "5528172c-40ad-11f0-9476-2e9782bd5fa7", "name": "Calculation response timeout (ms)", "creationDate": "2025-06-03T19:02:45.069+00:00", "valueType": "INTEGER", "value": {"@type": "String", "value": "120000"}}, {"persisted": true, "owner": "CYODA", "id": "55281970-40ad-11f0-9476-2e9782bd5fa7", "name": "Retry policy", "creationDate": "2025-06-03T19:02:45.069+00:00", "valueType": "STRING", "value": {"@type": "String", "value": "NONE"}}, {"persisted": true, "owner": "CYODA", "id": "552821d6-40ad-11f0-9476-2e9782bd5fa7", "name": "Tags for filtering calculation nodes (separated by ',' or ';')", "creationDate": "2025-06-03T19:02:45.069+00:00", "valueType": "STRING", "value": {"@type": "String", "value": "58cbeac6-3f0f-11b2-ba20-3e7b56738ce4"}}, {"persisted": true, "owner": "CYODA", "id": "55282398-40ad-11f0-9476-2e9782bd5fa7", "name": "Attach entity", "creationDate": "2025-06-03T19:02:45.069+00:00", "valueType": "STRING", "value": {"@type": "String", "value": "true"}}, {"persisted": true, "owner": "CYODA", "id": "55282578-40ad-11f0-9476-2e9782bd5fa7", "name": "Calculation response timeout (ms)", "creationDate": "2025-06-03T19:02:45.069+00:00", "valueType": "INTEGER", "value": {"@type": "String", "value": "120000"}}, {"persisted": true, "owner": "CYODA", "id": "5528274e-40ad-11f0-9476-2e9782bd5fa7", "name": "Retry policy", "creationDate": "2025-06-03T19:02:45.070+00:00", "valueType": "STRING", "value": {"@type": "String", "value": "NONE"}}, {"persisted": true, "owner": "CYODA", "id": "55282d98-40ad-11f0-9476-2e9782bd5fa7", "name": "Tags for filtering calculation nodes (separated by ',' or ';')", "creationDate": "2025-06-03T19:02:45.070+00:00", "valueType": "STRING", "value": {"@type": "String", "value": "58cbeac6-3f0f-11b2-ba20-3e7b56738ce4"}}, {"persisted": true, "owner": "CYODA", "id": "55282f78-40ad-11f0-9476-2e9782bd5fa7", "name": "Attach entity", "creationDate": "2025-06-03T19:02:45.070+00:00", "valueType": "STRING", "value": {"@type": "String", "value": "true"}}, {"persisted": true, "owner": "CYODA", "id": "55283162-40ad-11f0-9476-2e9782bd5fa7", "name": "Calculation response timeout (ms)", "creationDate": "2025-06-03T19:02:45.070+00:00", "valueType": "INTEGER", "value": {"@type": "String", "value": "120000"}}, {"persisted": true, "owner": "CYODA", "id": "55283356-40ad-11f0-9476-2e9782bd5fa7", "name": "Retry policy", "creationDate": "2025-06-03T19:02:45.070+00:00", "valueType": "STRING", "value": {"@type": "String", "value": "NONE"}}, {"persisted": true, "owner": "CYODA", "id": "55283a90-40ad-11f0-9476-2e9782bd5fa7", "name": "Tags for filtering calculation nodes (separated by ',' or ';')", "creationDate": "2025-06-03T19:02:45.070+00:00", "valueType": "STRING", "value": {"@type": "String", "value": "58cbeac6-3f0f-11b2-ba20-3e7b56738ce4"}}, {"persisted": true, "owner": "CYODA", "id": "55283c52-40ad-11f0-9476-2e9782bd5fa7", "name": "Attach entity", "creationDate": "2025-06-03T19:02:45.070+00:00", "valueType": "STRING", "value": {"@type": "String", "value": "true"}}, {"persisted": true, "owner": "CYODA", "id": "55283e64-40ad-11f0-9476-2e9782bd5fa7", "name": "Calculation response timeout (ms)", "creationDate": "2025-06-03T19:02:45.070+00:00", "valueType": "INTEGER", "value": {"@type": "String", "value": "120000"}}, {"persisted": true, "owner": "CYODA", "id": "5528408a-40ad-11f0-9476-2e9782bd5fa7", "name": "Retry policy", "creationDate": "2025-06-03T19:02:45.070+00:00", "valueType": "STRING", "value": {"@type": "String", "value": "NONE"}}]}